{
    "face": [
        "1",
        "2"
    ],
    "hat": [
        "curved",
        "pointy",
        "hood"
    ],
    "robe": [
        "open",
        "closed"
    ],
    "beard": [
        "1",
        "2",
        "3"
    ],
    "custom": {
        "BrainoidGames": "tank",
        "kuviman": "tank",
        "PomoTheDog": "pomo",
        "badcop_": "badcop",
        "kuviman": "kuviman",
        "HonestDanGames": "pighorse",
        "ElysiaGriffin": "lizard",
        "itsboats": "boat"
    }
}